README.md
pyproject.toml
setup.py
pygennor/__init__.py
pygennor.egg-info/PKG-INFO
pygennor.egg-info/SOURCES.txt
pygennor.egg-info/dependency_links.txt
pygennor.egg-info/top_level.txt