Metadata-Version: 2.1
Name: pygennor
Version: 0.1.0
Summary: premium proxies
Home-page: UNKNOWN
Author: bluesatan
License: MIT
Keywords: style
Platform: UNKNOWN
Classifier: Development Status :: 5 - Production/Stable
